odoo/addons/barcodes_generator_picking/README.rst
odoo/addons/barcodes_generator_picking/__init__.py
odoo/addons/barcodes_generator_picking/__manifest__.py
odoo/addons/barcodes_generator_picking/demo/barcode_rule.xml
odoo/addons/barcodes_generator_picking/demo/function.xml
odoo/addons/barcodes_generator_picking/demo/ir_sequence.xml
odoo/addons/barcodes_generator_picking/demo/stock_picking.xml
odoo/addons/barcodes_generator_picking/i18n/barcodes_generator_picking.pot
odoo/addons/barcodes_generator_picking/i18n/es.po
odoo/addons/barcodes_generator_picking/i18n/es_ES.po
odoo/addons/barcodes_generator_picking/i18n/fr.po
odoo/addons/barcodes_generator_picking/i18n/hr.po
odoo/addons/barcodes_generator_picking/i18n/nl_NL.po
odoo/addons/barcodes_generator_picking/models/__init__.py
odoo/addons/barcodes_generator_picking/models/barcode_rule.py
odoo/addons/barcodes_generator_picking/models/stock_picking.py
odoo/addons/barcodes_generator_picking/static/description/icon.png
odoo/addons/barcodes_generator_picking/static/description/stock_picking_sequence_generation.png
odoo/addons/barcodes_generator_picking/tests/__init__.py
odoo/addons/barcodes_generator_picking/tests/test_barcode_generator.py
odoo/addons/barcodes_generator_picking/views/stock_picking.xml
odoo11_addon_barcodes_generator_picking-11.0.1.0.0.99.dev2.dist-info/METADATA
odoo11_addon_barcodes_generator_picking-11.0.1.0.0.99.dev2.dist-info/RECORD
odoo11_addon_barcodes_generator_picking-11.0.1.0.0.99.dev2.dist-info/WHEEL
odoo11_addon_barcodes_generator_picking-11.0.1.0.0.99.dev2.dist-info/top_level.txt
